{
  "photoset": {
    "id": "305693",
    "primary": "12524834",
    "owner": "29556254@N00",
    "ownername": "roobottom",
    "photo": [
      {
        "id": "12524834",
        "secret": "4154177d14",
        "server": "9",
        "farm": 1,
        "title": "Jim and Dan play the blues",
        "isprimary": "1",
        "ispublic": 1,
        "isfriend": 0,
        "isfamily": 0,
        "url_o": "https://farm1.staticflickr.com/9/12524834_4154177d14_o.jpg",
        "height_o": "1200",
        "width_o": "1600",
        "url_s": "https://farm1.staticflickr.com/9/12524834_4154177d14_m.jpg",
        "height_s": "180",
        "width_s": "240"
      },
      {
        "id": "12525022",
        "secret": "93e27046a2",
        "server": "11",
        "farm": 1,
        "title": "Jim and Dan",
        "isprimary": "0",
        "ispublic": 1,
        "isfriend": 0,
        "isfamily": 0,
        "url_o": "https://farm1.staticflickr.com/11/12525022_93e27046a2_o.jpg",
        "height_o": "1200",
        "width_o": "1600",
        "url_s": "https://farm1.staticflickr.com/11/12525022_93e27046a2_m.jpg",
        "height_s": "180",
        "width_s": "240"
      },
      {
        "id": "12524954",
        "secret": "0afebfa888",
        "server": "10",
        "farm": 1,
        "title": "live in walsall",
        "isprimary": "0",
        "ispublic": 1,
        "isfriend": 0,
        "isfamily": 0,
        "url_o": "https://farm1.staticflickr.com/10/12524954_0afebfa888_o.jpg",
        "height_o": "1200",
        "width_o": "1600",
        "url_s": "https://farm1.staticflickr.com/10/12524954_0afebfa888_m.jpg",
        "height_s": "180",
        "width_s": "240"
      },
      {
        "id": "12524899",
        "secret": "bcaad15336",
        "server": "8",
        "farm": 1,
        "title": "Dave n Dan",
        "isprimary": "0",
        "ispublic": 1,
        "isfriend": 0,
        "isfamily": 0,
        "url_o": "https://farm1.staticflickr.com/8/12524899_bcaad15336_o.jpg",
        "height_o": "1200",
        "width_o": "1600",
        "url_s": "https://farm1.staticflickr.com/8/12524899_bcaad15336_m.jpg",
        "height_s": "180",
        "width_s": "240"
      },
      {
        "id": "12524923",
        "secret": "66ab2f7cff",
        "server": "10",
        "farm": 1,
        "title": "Dave",
        "isprimary": "0",
        "ispublic": 1,
        "isfriend": 0,
        "isfamily": 0,
        "url_o": "https://farm1.staticflickr.com/10/12524923_66ab2f7cff_o.jpg",
        "height_o": "1200",
        "width_o": "1600",
        "url_s": "https://farm1.staticflickr.com/10/12524923_66ab2f7cff_m.jpg",
        "height_s": "180",
        "width_s": "240"
      },
      {
        "id": "12524873",
        "secret": "f4cc5b730e",
        "server": "10",
        "farm": 1,
        "title": "Jiiiiim",
        "isprimary": "0",
        "ispublic": 1,
        "isfriend": 0,
        "isfamily": 0,
        "url_o": "https://farm1.staticflickr.com/10/12524873_f4cc5b730e_o.jpg",
        "height_o": "1200",
        "width_o": "1600",
        "url_s": "https://farm1.staticflickr.com/10/12524873_f4cc5b730e_m.jpg",
        "height_s": "180",
        "width_s": "240"
      }
    ],
    "page": "1",
    "per_page": 500,
    "perpage": 500,
    "pages": 1,
    "total": "6",
    "title": "Acoustic Night"
  },
  "stat": "ok"
}
