{
  "photoset": {
    "id": "850147",
    "primary": "38566649",
    "owner": "29556254@N00",
    "ownername": "roobottom",
    "photo": [
      {
        "id": "38566649",
        "secret": "ce2c74d726",
        "server": "30",
        "farm": 1,
        "title": "A Plane In The Grass",
        "isprimary": "1",
        "ispublic": 1,
        "isfriend": 0,
        "isfamily": 0,
        "url_o": "https://farm1.staticflickr.com/30/38566649_ce2c74d726_o.jpg",
        "height_o": "1728",
        "width_o": "2304",
        "url_s": "https://farm1.staticflickr.com/30/38566649_ce2c74d726_m.jpg",
        "height_s": "180",
        "width_s": "240"
      },
      {
        "id": "38564284",
        "secret": "d4146529dd",
        "server": "29",
        "farm": 1,
        "title": "Cockpit",
        "isprimary": "0",
        "ispublic": 1,
        "isfriend": 0,
        "isfamily": 0,
        "url_o": "https://farm1.staticflickr.com/29/38564284_d4146529dd_o.jpg",
        "height_o": "1728",
        "width_o": "2304",
        "url_s": "https://farm1.staticflickr.com/29/38564284_d4146529dd_m.jpg",
        "height_s": "180",
        "width_s": "240"
      },
      {
        "id": "38564447",
        "secret": "da9c988fd6",
        "server": "23",
        "farm": 1,
        "title": "Point",
        "isprimary": "0",
        "ispublic": 1,
        "isfriend": 0,
        "isfamily": 0,
        "url_o": "https://farm1.staticflickr.com/23/38564447_da9c988fd6_o.jpg",
        "height_o": "1728",
        "width_o": "2304",
        "url_s": "https://farm1.staticflickr.com/23/38564447_da9c988fd6_m.jpg",
        "height_s": "180",
        "width_s": "240"
      },
      {
        "id": "38564659",
        "secret": "5b0ab5d9f9",
        "server": "23",
        "farm": 1,
        "title": "Point II",
        "isprimary": "0",
        "ispublic": 1,
        "isfriend": 0,
        "isfamily": 0,
        "url_o": "https://farm1.staticflickr.com/23/38564659_5b0ab5d9f9_o.jpg",
        "height_o": "1728",
        "width_o": "2304",
        "url_s": "https://farm1.staticflickr.com/23/38564659_5b0ab5d9f9_m.jpg",
        "height_s": "180",
        "width_s": "240"
      },
      {
        "id": "38564816",
        "secret": "314358ea3a",
        "server": "29",
        "farm": 1,
        "title": "Prop Nose Cone",
        "isprimary": "0",
        "ispublic": 1,
        "isfriend": 0,
        "isfamily": 0,
        "url_o": "https://farm1.staticflickr.com/29/38564816_314358ea3a_o.jpg",
        "height_o": "1728",
        "width_o": "2304",
        "url_s": "https://farm1.staticflickr.com/29/38564816_314358ea3a_m.jpg",
        "height_s": "180",
        "width_s": "240"
      },
      {
        "id": "38565093",
        "secret": "742ff60d3e",
        "server": "33",
        "farm": 1,
        "title": "Wheel Light",
        "isprimary": "0",
        "ispublic": 1,
        "isfriend": 0,
        "isfamily": 0,
        "url_o": "https://farm1.staticflickr.com/33/38565093_742ff60d3e_o.jpg",
        "height_o": "2304",
        "width_o": "1728",
        "url_s": "https://farm1.staticflickr.com/33/38565093_742ff60d3e_m.jpg",
        "height_s": "240",
        "width_s": "180"
      },
      {
        "id": "38565304",
        "secret": "5b7cf1a5d5",
        "server": "28",
        "farm": 1,
        "title": "Just £35 From Tyre Traders",
        "isprimary": "0",
        "ispublic": 1,
        "isfriend": 0,
        "isfamily": 0,
        "url_o": "https://farm1.staticflickr.com/28/38565304_5b7cf1a5d5_o.jpg",
        "height_o": "1728",
        "width_o": "2304",
        "url_s": "https://farm1.staticflickr.com/28/38565304_5b7cf1a5d5_m.jpg",
        "height_s": "180",
        "width_s": "240"
      },
      {
        "id": "38565528",
        "secret": "2cef290911",
        "server": "26",
        "farm": 1,
        "title": "Big Hooter",
        "isprimary": "0",
        "ispublic": 1,
        "isfriend": 0,
        "isfamily": 0,
        "url_o": "https://farm1.staticflickr.com/26/38565528_2cef290911_o.jpg",
        "height_o": "1728",
        "width_o": "2304",
        "url_s": "https://farm1.staticflickr.com/26/38565528_2cef290911_m.jpg",
        "height_s": "180",
        "width_s": "240"
      },
      {
        "id": "38565747",
        "secret": "39f7ab66a6",
        "server": "32",
        "farm": 1,
        "title": "Bombs Away!",
        "isprimary": "0",
        "ispublic": 1,
        "isfriend": 0,
        "isfamily": 0,
        "url_o": "https://farm1.staticflickr.com/32/38565747_39f7ab66a6_o.jpg",
        "height_o": "1728",
        "width_o": "2304",
        "url_s": "https://farm1.staticflickr.com/32/38565747_39f7ab66a6_m.jpg",
        "height_s": "180",
        "width_s": "240"
      },
      {
        "id": "38566053",
        "secret": "4600f8c177",
        "server": "29",
        "farm": 1,
        "title": "Mirror Time",
        "isprimary": "0",
        "ispublic": 1,
        "isfriend": 0,
        "isfamily": 0,
        "url_o": "https://farm1.staticflickr.com/29/38566053_4600f8c177_o.jpg",
        "height_o": "1728",
        "width_o": "2304",
        "url_s": "https://farm1.staticflickr.com/29/38566053_4600f8c177_m.jpg",
        "height_s": "180",
        "width_s": "240"
      },
      {
        "id": "38566356",
        "secret": "a0d4e9d0c1",
        "server": "21",
        "farm": 1,
        "title": "Danger Danger Danger",
        "isprimary": "0",
        "ispublic": 1,
        "isfriend": 0,
        "isfamily": 0,
        "url_o": "https://farm1.staticflickr.com/21/38566356_a0d4e9d0c1_o.jpg",
        "height_o": "1728",
        "width_o": "2304",
        "url_s": "https://farm1.staticflickr.com/21/38566356_a0d4e9d0c1_m.jpg",
        "height_s": "180",
        "width_s": "240"
      },
      {
        "id": "38567026",
        "secret": "9a1a9afa20",
        "server": "25",
        "farm": 1,
        "title": "Spitfire Simulator",
        "isprimary": "0",
        "ispublic": 1,
        "isfriend": 0,
        "isfamily": 0,
        "url_o": "https://farm1.staticflickr.com/25/38567026_9a1a9afa20_o.jpg",
        "height_o": "1728",
        "width_o": "2304",
        "url_s": "https://farm1.staticflickr.com/25/38567026_9a1a9afa20_m.jpg",
        "height_s": "180",
        "width_s": "240"
      },
      {
        "id": "38567275",
        "secret": "58fbf37238",
        "server": "22",
        "farm": 1,
        "title": "Han, Cheris and The Engine",
        "isprimary": "0",
        "ispublic": 1,
        "isfriend": 0,
        "isfamily": 0,
        "url_o": "https://farm1.staticflickr.com/22/38567275_58fbf37238_o.jpg",
        "height_o": "1728",
        "width_o": "2304",
        "url_s": "https://farm1.staticflickr.com/22/38567275_58fbf37238_m.jpg",
        "height_s": "180",
        "width_s": "240"
      },
      {
        "id": "38567500",
        "secret": "deab23d3b4",
        "server": "24",
        "farm": 1,
        "title": "Huge Blades",
        "isprimary": "0",
        "ispublic": 1,
        "isfriend": 0,
        "isfamily": 0,
        "url_o": "https://farm1.staticflickr.com/24/38567500_deab23d3b4_o.jpg",
        "height_o": "1728",
        "width_o": "2304",
        "url_s": "https://farm1.staticflickr.com/24/38567500_deab23d3b4_m.jpg",
        "height_s": "180",
        "width_s": "240"
      },
      {
        "id": "38567779",
        "secret": "954bfc2476",
        "server": "27",
        "farm": 1,
        "title": "Flyboy Stix",
        "isprimary": "0",
        "ispublic": 1,
        "isfriend": 0,
        "isfamily": 0,
        "url_o": "https://farm1.staticflickr.com/27/38567779_954bfc2476_o.jpg",
        "height_o": "1728",
        "width_o": "2304",
        "url_s": "https://farm1.staticflickr.com/27/38567779_954bfc2476_m.jpg",
        "height_s": "180",
        "width_s": "240"
      },
      {
        "id": "38568042",
        "secret": "74c4de86bf",
        "server": "29",
        "farm": 1,
        "title": "The Bell Inn",
        "isprimary": "0",
        "ispublic": 1,
        "isfriend": 0,
        "isfamily": 0,
        "url_o": "https://farm1.staticflickr.com/29/38568042_74c4de86bf_o.jpg",
        "height_o": "1728",
        "width_o": "2304",
        "url_s": "https://farm1.staticflickr.com/29/38568042_74c4de86bf_m.jpg",
        "height_s": "180",
        "width_s": "240"
      },
      {
        "id": "38568266",
        "secret": "39e63e8765",
        "server": "27",
        "farm": 1,
        "title": "Lunch",
        "isprimary": "0",
        "ispublic": 1,
        "isfriend": 0,
        "isfamily": 0,
        "url_o": "https://farm1.staticflickr.com/27/38568266_39e63e8765_o.jpg",
        "height_o": "1728",
        "width_o": "2304",
        "url_s": "https://farm1.staticflickr.com/27/38568266_39e63e8765_m.jpg",
        "height_s": "180",
        "width_s": "240"
      }
    ],
    "page": "1",
    "per_page": 500,
    "perpage": 500,
    "pages": 1,
    "total": "17",
    "title": "Cosford"
  },
  "stat": "ok"
}
